.DS_Store
gallery_get/__init__.py
gallery_get/__main__.py
gallery_get/gallery_get.py
gallery_get/gallery_get_test.py
gallery_get/gallery_utils.py
gallery_get/reddit_get.py
gallery_get/gallery_plugins/__init__.py
gallery_get/gallery_plugins/plugin_4chan.py
gallery_get/gallery_plugins/plugin_alphacoders.py
gallery_get/gallery_plugins/plugin_eroshare.py
gallery_get/gallery_plugins/plugin_fuskator.py
gallery_get/gallery_plugins/plugin_generic.py
gallery_get/gallery_plugins/plugin_gfycat.py
gallery_get/gallery_plugins/plugin_gogoimage.py
gallery_get/gallery_plugins/plugin_imagebam.py
gallery_get/gallery_plugins/plugin_imagefap.py
gallery_get/gallery_plugins/plugin_imagefaq_info.py
gallery_get/gallery_plugins/plugin_imagevenue.py
gallery_get/gallery_plugins/plugin_imgbox.py
gallery_get/gallery_plugins/plugin_imgur_album.py
gallery_get/gallery_plugins/plugin_pornhub_album.py
gallery_get/gallery_plugins/plugin_pornhub_video.py
gallery_get/gallery_plugins/plugin_reddit_gallery.py
gallery_get/gallery_plugins/plugin_shimmie.py
gallery_get/gallery_plugins/plugin_vidble.py
gallery_get/gallery_plugins/plugin_vk.py
gallery_get/gallery_plugins/plugin_xHamster.py
gallery_get/gallery_plugins/plugin_xVideos.py
gallery_get/gallery_plugins/plugin_xVideos_gallery.py
gallery_plugins/__init__.py
gallery_plugins/plugin_4chan.py
gallery_plugins/plugin_alphacoders.py
gallery_plugins/plugin_eroshare.py
gallery_plugins/plugin_fuskator.py
gallery_plugins/plugin_generic.py
gallery_plugins/plugin_gfycat.py
gallery_plugins/plugin_gogoimage.py
gallery_plugins/plugin_imagebam.py
gallery_plugins/plugin_imagefap.py
gallery_plugins/plugin_imagefaq_info.py
gallery_plugins/plugin_imagevenue.py
gallery_plugins/plugin_imgbox.py
gallery_plugins/plugin_imgur_album.py
gallery_plugins/plugin_pornhub_album.py
gallery_plugins/plugin_pornhub_video.py
gallery_plugins/plugin_reddit_gallery.py
gallery_plugins/plugin_shimmie.py
gallery_plugins/plugin_vidble.py
gallery_plugins/plugin_vk.py
gallery_get-1.9.4.dist-info/LICENSE.txt
gallery_get-1.9.4.dist-info/METADATA
gallery_get-1.9.4.dist-info/WHEEL
gallery_get-1.9.4.dist-info/entry_points.txt
gallery_get-1.9.4.dist-info/top_level.txt
gallery_get-1.9.4.dist-info/RECORD
