Metadata-Version: 2.1
Name: gallery-get
Version: 1.9.4
Summary: Gallery downloader - supports many galleries and reddit user histories
Home-page: https://github.com/regosen/gallery_get
Author: Rego Sen
Author-email: regosen@gmail.com
License: MIT
Keywords: gallery downloader reddit imgur imgbox 4chan xhamster eroshare vidble pornhub xvideos imagebam alphacoders
Platform: UNKNOWN
Classifier: Development Status :: 4 - Beta
Classifier: Environment :: Console
Classifier: Intended Audience :: End Users/Desktop
Classifier: License :: OSI Approved :: MIT License
Classifier: Operating System :: OS Independent
Classifier: Programming Language :: Python
Classifier: Programming Language :: Python :: 2
Classifier: Programming Language :: Python :: 3
Classifier: Topic :: Internet
Classifier: Topic :: Multimedia :: Graphics
License-File: LICENSE.txt
Requires-Dist: chromedriver-py
Requires-Dist: selenium
